swip/__init__.py
swip/swip.py
swip/commands/__init__.py
swip/commands/add.py
swip/commands/branch.py
swip/commands/checkout.py
swip/commands/commit.py
swip/commands/init.py
swip/commands/log.py
swip/commands/merge.py
swip/commands/status.py
swip/common/__init__.py
swip/common/exceptions.py
swip/common/helpers.py
swip/common/paths.py
swip-0.1.7.dist-info/LICENSE
swip-0.1.7.dist-info/METADATA
swip-0.1.7.dist-info/WHEEL
swip-0.1.7.dist-info/entry_points.txt
swip-0.1.7.dist-info/top_level.txt
swip-0.1.7.dist-info/RECORD
